{"name": "Waskish Beings", "short_name": "WAS", "state": "MN", "home_stadium": "{\"name\": \"Beings Field\", \"state\": \"MN\", \"fan_capacity\": 42597, \"air_temperature\": 76.45472633729929, \"wind_speed\": 8.91753391483453, \"field_distances\": {\"left\": 335.9170747844918, \"center\": 399.4226715733543, \"right\": 336.91255495122}}", "forty_man_roster": "[\"Betty Negro\", \"Robert Jenkins\", \"Hubert Smith\", \"Michael Strickland\", \"David Krueger\", \"Roger Holland\", \"Michael Hale\", \"Joel Riley\", \"Harry Brownlee\", \"Clarence Smith\", \"Patricia Jones\", \"Christopher Boyle\", \"Jimmy Johnson\", \"Amanda Todd\", \"Leon Hall\", \"David Callicutt\", \"Danielle Wile\", \"John Miller\", \"Daniella Dax\", \"Gloria Gonzalez\", \"Caleb Smith\", \"Rosemary Tipka\", \"Regina Reid\", \"Justin Devilla\", \"Leonard Ray\", \"Valerie Katz\", \"Corey Martin\", \"Karl Currence\", \"Timothy Palmer\", \"Helen Robbins\", \"Phil Kam\", \"James Davis\", \"Robert Devito\", \"Paul Barber\", \"Michael Mclain\", \"Stephen Brenneman\", \"Delma Bearman\", \"Alfredo Smith\", \"Timothy Collins\", \"Christopher Kolle\"]", "active_roster": "[\"Christopher Kolle\", \"Timothy Collins\", \"Alfredo Smith\", \"Delma Bearman\", \"Stephen Brenneman\", \"Michael Mclain\", \"Paul Barber\", \"Robert Devito\", \"James Davis\", \"Phil Kam\", \"Helen Robbins\", \"Timothy Palmer\", \"Karl Currence\", \"Corey Martin\", \"Valerie Katz\", \"Leonard Ray\", \"Justin Devilla\", \"Regina Reid\", \"Rosemary Tipka\", \"Caleb Smith\", \"Gloria Gonzalez\", \"Daniella Dax\", \"John Miller\", \"Danielle Wile\", \"David Callicutt\", \"Leon Hall\", \"Amanda Todd\", \"Jimmy Johnson\", \"Christopher Boyle\"]", "lineup": "[\"Leonard Ray\", \"Christopher Boyle\", \"Corey Martin\", \"John Miller\", \"Karl Currence\", \"Daniella Dax\", \"Caleb Smith\", \"Gloria Gonzalez\", \"Valerie Katz\", \"Phil Kam\"]", "stats": "{\"wins\": 0, \"losses\": 0, \"runs_scored\": 0, \"runs_against\": 0}", "strategy": 2, "division": "NL West"}